uc2rest/UC2Client.py
uc2rest/__init__.py
uc2rest/__version__.py
uc2rest/analog.py
uc2rest/camera.py
uc2rest/config.py
uc2rest/config_.py
uc2rest/digitalout.py
uc2rest/galvo.py
uc2rest/home.py
uc2rest/laser.py
uc2rest/ledmatrix.py
uc2rest/logger.py
uc2rest/modules.py
uc2rest/motor.py
uc2rest/mserial.py
uc2rest/pid.py
uc2rest/slm.py
uc2rest/state.py
uc2rest/updater.py
uc2rest/utils.py
uc2rest/wifi.py
UC2_REST-2.1.0.dist-info/LICENSE
UC2_REST-2.1.0.dist-info/METADATA
UC2_REST-2.1.0.dist-info/WHEEL
UC2_REST-2.1.0.dist-info/top_level.txt
UC2_REST-2.1.0.dist-info/RECORD
