Metadata-Version: 2.1
Name: UC2-REST
Version: 2.1.0
Summary: This pacage will help you to drive the ESP32-driven microscopy control modules from UC2
Home-page: https://github.com/openUC2/UC2-REST
Author: Benedict Diederich
Author-email: benedictdied@gmail.com
License: GPL v3
Keywords: UC2REST API to control ESP32-driven microscopy control boards
Classifier: Development Status :: 4 - Beta
Classifier: Intended Audience :: Developers
Classifier: Programming Language :: Python :: 3.7
Requires-Python: >=3.7
License-File: LICENSE
Requires-Dist: numpy
Requires-Dist: requests
Requires-Dist: pyserial
Requires-Dist: esptool
Requires-Dist: progressbar2
Requires-Dist: pillow
